stempl_flask/__init__.py
stempl_flask-1.0.1.dist-info/LICENSE
stempl_flask-1.0.1.dist-info/METADATA
stempl_flask-1.0.1.dist-info/WHEEL
stempl_flask-1.0.1.dist-info/top_level.txt
stempl_flask-1.0.1.dist-info/RECORD
