Metadata-Version: 2.1
Name: stempl-flask
Version: 1.0.1
Summary: A Flask project template for serpent-cli
Author-email: Carl Furtado <carlzfurtado@gmail.com>
License: The MIT License (MIT)
Project-URL: Home, https://github.com/User0332/serpent/templatespack/flask
Classifier: License :: OSI Approved :: MIT License
License-File: LICENSE
Requires-Dist: flask
